tarwiiga/__init__.py
tarwiiga/config.py
tarwiiga/env
tarwiiga/llm.py
tarwiiga/adgen/__init__.py
tarwiiga/adgen/google_ads/__init__.py
tarwiiga/adgen/google_ads/call_ad_generator.py
tarwiiga/adgen/google_ads/call_ad_publisher.py
tarwiiga/adgen/google_ads/creator/__init__.py
tarwiiga/adgen/google_ads/creator/account.py
tarwiiga/adgen/google_ads/creator/ad_group.py
tarwiiga/adgen/google_ads/creator/campaign.py
tarwiiga/adgen/google_ads/creator/client.py
tarwiiga/scrapper/__init__.py
tarwiiga/scrapper/posts_scrapper.py
tarwiiga/sitegen/__init__.py
tarwiiga/sitegen/generator.py
tarwiiga/sitegen/publisher.py
tarwiiga-1.1.4.dist-info/METADATA
tarwiiga-1.1.4.dist-info/WHEEL
tarwiiga-1.1.4.dist-info/licenses/LICENSE
tarwiiga-1.1.4.dist-info/RECORD
