Metadata-Version: 2.3
Name: tarwiiga
Version: 1.1.4
Summary: Tarwiiga Python Package
Project-URL: Homepage, https://github.com/tarwiiga/tarwiiga
Project-URL: Documentation, https://docs.tarwiiga.com
Project-URL: Issues, https://github.com/tarwiiga/tarwiiga/issues
Author-email: Tarwiiga <tarwiiga@gmail.com>
License-File: LICENSE
Classifier: License :: OSI Approved :: MIT License
Classifier: Operating System :: OS Independent
Classifier: Programming Language :: Python :: 3
Requires-Python: >=3.11
Requires-Dist: gitpython
Requires-Dist: google-ads
Requires-Dist: langchain
Requires-Dist: langchain-anthropic
Requires-Dist: langchain-google-genai
Requires-Dist: langchain-groq
Requires-Dist: langchain-openai
Requires-Dist: langchain-together
Requires-Dist: python-decouple
